track_sort_py-0.3.1.dist-info/METADATA
track_sort_py-0.3.1.dist-info/WHEEL
track_sort_py-0.3.1.dist-info/licenses/LICENSE
track_sort/__init__.py
track_sort/track_sort.abi3.so
track_sort_py-0.3.1.dist-info/RECORD
