Metadata-Version: 2.4
Name: track-sort-py
Version: 0.3.1
License-File: LICENSE
Summary: High Performance implementation of the SORT object tracking algorithm
Keywords: rust,object-tracking
Home-Page: https://gitlab.com/leandrosansilva/track-sort-py
License: Apache-2.0
Project-URL: Source Code, https://gitlab.com/leandrosansilva/track-sort-py.git
